CHANGES.txt
LICENSE.txt
MANIFEST.in
README.md
TODO.md
setup.py
onion_proctor.egg-info/PKG-INFO
onion_proctor.egg-info/SOURCES.txt
onion_proctor.egg-info/dependency_links.txt
onion_proctor.egg-info/entry_points.txt
onion_proctor.egg-info/not-zip-safe
onion_proctor.egg-info/requires.txt
onion_proctor.egg-info/top_level.txt
proctor/__init__.py
proctor/proxy.py
proctor/scripts.py
proctor/socket.py
proctor/tor.py
proctor/vendor/__init__.py
proctor/vendor/exit.py