Metadata-Version: 1.1
Name: onion-proctor
Version: 0.1.2
Summary: Proctor is an HTTP proxy that will distribute requests across a number of managed Tor circuits
Home-page: http://pypi.python.org/pypi/onion-proctor
Author: Nicolas Cadou
Author-email: ncadou@cadou.ca
License: LICENSE.txt
Platform: UNKNOWN
Classifier: Development Status :: 3 - Alpha
Classifier: Environment :: Plugins
Classifier: Intended Audience :: Developers
Classifier: Natural Language :: English
Classifier: Programming Language :: Python
Classifier: Programming Language :: Python :: 2.7
Classifier: Topic :: Documentation
Classifier: Topic :: Software Development :: Libraries :: Python Modules
Classifier: Topic :: Internet :: WWW/HTTP
